README.md
setup.py
pykovi/__init__.py
pykovi/cli.py
pykovi/glue_jobs.py
pykovi/glue_mock.py
pykovi/pandas_mock.py
pykovi/s3_mock.py
pykovi/session_mock.py
pykovi/utils.py
pykovi.egg-info/PKG-INFO
pykovi.egg-info/SOURCES.txt
pykovi.egg-info/dependency_links.txt
pykovi.egg-info/entry_points.txt
pykovi.egg-info/requires.txt
pykovi.egg-info/top_level.txt